pylinecount/__init__.py
pylinecount/__main__.py
pylinecount/pylinecount.py
pylinecount-0.1.dist-info/LICENSE
pylinecount-0.1.dist-info/METADATA
pylinecount-0.1.dist-info/WHEEL
pylinecount-0.1.dist-info/top_level.txt
pylinecount-0.1.dist-info/RECORD
